sysmon_utils/__init__.py
sysmon_utils/commands/__init__.py
sysmon_utils/commands/main_app.py
sysmon_utils/config.py
sysmon_utils/main.py
sysmon_utils/utils/__init__.py
sysmon_utils/utils/arg_definitions.py
sysmon_utils/utils/dataset.py
sysmon_utils/utils/events.py
sysmon_utils/utils/filters.py
sysmon_utils/utils/merge.py
sysmon_utils/utils/rules.py
sysmon_utils-0.1.2.dist-info/LICENSE
sysmon_utils-0.1.2.dist-info/METADATA
sysmon_utils-0.1.2.dist-info/WHEEL
sysmon_utils-0.1.2.dist-info/entry_points.txt
sysmon_utils-0.1.2.dist-info/RECORD
