Metadata-Version: 2.1
Name: sysmon-utils
Version: 0.1.2
Summary: A tool for working with and testing Sysmon configs.
License: MIT
Author: Connor Shade
Author-email: cnnrshd@gmail.com
Requires-Python: >=3.10,<4.0
Classifier: License :: OSI Approved :: MIT License
Classifier: Programming Language :: Python :: 3
Classifier: Programming Language :: Python :: 3.10
Classifier: Programming Language :: Python :: 3.11
Requires-Dist: PyYAML (>=6.0,<7.0)
Requires-Dist: lxml (>=4.9.2,<5.0.0)
Requires-Dist: packaging (>=23.1,<24.0)
Requires-Dist: rich (>=13.3.5,<14.0.0)
Requires-Dist: typer[all] (>=0.9.0,<0.10.0)
